neato_coding_challenge_tcp_client/__init__.py
neato_coding_challenge_tcp_client/__main__.py
neato_coding_challenge_tcp_client/py.typed
neato_coding_challenge_tcp_client-0.0.1.dist-info/entry_points.txt
neato_coding_challenge_tcp_client-0.0.1.dist-info/LICENSE.rst
neato_coding_challenge_tcp_client-0.0.1.dist-info/WHEEL
neato_coding_challenge_tcp_client-0.0.1.dist-info/METADATA
neato_coding_challenge_tcp_client-0.0.1.dist-info/RECORD
