Metadata-Version: 2.1
Name: neato-coding-challenge-tcp-client
Version: 0.0.1
Summary: Neato Coding Challenge - TCP Client
Home-page: https://github.com/neato-coding-challenge/tcp-client
License: MIT
Author: Michele Cardone
Author-email: michele.cardone82@gmail.com
Requires-Python: >=3.6.1,<4.0.0
Classifier: License :: OSI Approved :: MIT License
Classifier: Programming Language :: Python :: 3
Classifier: Programming Language :: Python :: 3.6
Classifier: Programming Language :: Python :: 3.7
Classifier: Programming Language :: Python :: 3.8
Requires-Dist: click (>=7.0,<8.0)
Project-URL: Changelog, https://github.com/neato-coding-challenge/tcp-client/releases
Project-URL: Documentation, https://neato-coding-challenge-tcp-client.readthedocs.io
Project-URL: Repository, https://github.com/neato-coding-challenge/tcp-client
